LICENSE.md
netport/__init__.py
netport/common.py
netport/database.py
netport/netport.py
scripts/__init__.py
scripts/cli.py
netport-0.4.0.dist-info/entry_points.txt
netport-0.4.0.dist-info/LICENSE.md
netport-0.4.0.dist-info/WHEEL
netport-0.4.0.dist-info/METADATA
netport-0.4.0.dist-info/RECORD
